{
  "db_name": "MySQL",
  "query": "\nUPDATE generic_inference_jobs\nSET\n  status = ?,\n  on_success_result_entity_type = ?,\n  on_success_result_entity_token = ?,\n  failure_reason = NULL,\n  internal_debugging_failure_reason = NULL,\n  success_execution_millis = NULL,\n  success_inference_execution_millis = NULL,\n  retry_at = NULL,\n  successfully_completed_at = NOW()\nWHERE token = ?\n        ",
  "describe": {
    "columns": [],
    "parameters": {
      "Right": 4
    },
    "nullable": []
  },
  "hash": "f68a8917e639418a0bb952bef606c96299001e143c745ee30df99b72d1235d35"
}
